disk_smart_tool/__init__.py
disk_smart_tool/smart.py
disk_smart_tool/smart_tool.py
disk_smart_tool-0.0.1.dist-info/LICENSE
disk_smart_tool-0.0.1.dist-info/METADATA
disk_smart_tool-0.0.1.dist-info/WHEEL
disk_smart_tool-0.0.1.dist-info/top_level.txt
disk_smart_tool-0.0.1.dist-info/RECORD
